msad/__init__.py
msad/__main__.py
msad/ad.py
msad/group.py
msad/main.py
msad/search.py
msad/user.py
msad-0.4.1.dist-info/METADATA
msad-0.4.1.dist-info/WHEEL
msad-0.4.1.dist-info/entry_points.txt
msad-0.4.1.dist-info/licenses/LICENSE
msad-0.4.1.dist-info/RECORD
