Metadata-Version: 2.4
Name: msad
Version: 0.4.1
Summary: msad is a commandline for interacting with Active Directory
Project-URL: Homepage, https://github.com/matteoredaelli/msad
Project-URL: Issues, https://github.com/matteoredaelli/msad/issues
Author-email: Matteo Redaelli <matteo.redaelli@gmail.com>
License-Expression: GPL-3.0-or-later
License-File: LICENSE
Classifier: Operating System :: OS Independent
Classifier: Programming Language :: Python :: 3
Requires-Python: >=3.11
Requires-Dist: cryptography
Requires-Dist: gssapi
Requires-Dist: ldap3
Requires-Dist: typer
